MadeLibLBL/AWSBedrockUtils.py
MadeLibLBL/AWSOpenSearchUtils.py
MadeLibLBL/AWSS3Utils.py
MadeLibLBL/DataframeUtils.py
MadeLibLBL/DebugHelper.py
MadeLibLBL/FrontCharla.py
MadeLibLBL/FrontStreamlit.py
MadeLibLBL/TextManipulation.py
MadeLibLBL/__init__.py
madeliblbl-2025.7.7.dist-info/METADATA
madeliblbl-2025.7.7.dist-info/WHEEL
madeliblbl-2025.7.7.dist-info/licenses/LICENSE.txt
madeliblbl-2025.7.7.dist-info/RECORD
