Metadata-Version: 2.4
Name: MadeLibLBL
Version: 2025.7.7
Summary: My daily use functions at Made
Project-URL: Repository, https://github.com/luizalaquini/MadeLibLBL
Author-email: Luiza Batista Laquini <luizablaquini@hotmail.com>
License-Expression: MIT
License-File: LICENSE.txt
Keywords: helpers,utils
Classifier: Development Status :: 3 - Alpha
Classifier: Operating System :: OS Independent
Classifier: Programming Language :: Python
Requires-Python: >=3.10
Requires-Dist: pandas>=2.2.2
